gym_luckyworld/__init__.py
gym_luckyworld/env.py
gym_luckyworld/task.py
gym_luckyworld-0.0.20.dist-info/LICENSE
gym_luckyworld-0.0.20.dist-info/METADATA
gym_luckyworld-0.0.20.dist-info/WHEEL
gym_luckyworld-0.0.20.dist-info/RECORD
