Metadata-Version: 2.3
Name: gym-luckyworld
Version: 0.0.20
Summary: A gym environment for LuckyWorld
License: MIT
Keywords: robotics,deep,reinforcement,learning,luckyworld,environment,gym,gymnasium,mujoco
Author: Ethan M. Clark
Author-email: eclark715@gmail.com
Requires-Python: >=3.10,<4.0
Classifier: Development Status :: 3 - Alpha
Classifier: Intended Audience :: Developers
Classifier: License :: OSI Approved :: Apache Software License
Classifier: License :: OSI Approved :: MIT License
Classifier: Programming Language :: Python :: 3
Classifier: Programming Language :: Python :: 3.10
Classifier: Programming Language :: Python :: 3.11
Classifier: Programming Language :: Python :: 3.12
Classifier: Programming Language :: Python :: 3.13
Classifier: Topic :: Software Development :: Build Tools
Provides-Extra: dev
Provides-Extra: test
Requires-Dist: debugpy (>=1.8.1) ; extra == "dev"
Requires-Dist: gymnasium (>=0.29.1)
Requires-Dist: imageio[ffmpeg] (>=2.34.0)
Requires-Dist: luckyrobots (>=0.1.67)
Requires-Dist: omegaconf (>=2.3.0)
Requires-Dist: pre-commit (>=3.7.0) ; extra == "dev"
Requires-Dist: pytest (>=8.1.0) ; extra == "test"
Requires-Dist: pytest-cov (>=5.0.0) ; extra == "test"
